cvpc/__init__.py
cvpc/__main__.py
cvpc/arguments.py
cvpc/entrypoint.py
cvpc/aio/__init__.py
cvpc/aio/policy.py
cvpc/aio/run.py
cvpc/apps/__init__.py
cvpc/apps/master/__init__.py
cvpc/assets/__init__.py
cvpc/logging/__init__.py
cvpc/logging/logging.py
cvpc/logging/formatters/__init__.py
cvpc/logging/formatters/colored.py
cvpc/system/__init__.py
cvpc/system/environ.py
cvpc/types/__init__.py
cvpc/types/override.py
cvpc/types/string/__init__.py
cvpc/types/string/to_boolean.py
cvpc-0.0.3.dist-info/licenses/LICENSE
cvpc-0.0.3.dist-info/METADATA
cvpc-0.0.3.dist-info/WHEEL
cvpc-0.0.3.dist-info/entry_points.txt
cvpc-0.0.3.dist-info/top_level.txt
cvpc-0.0.3.dist-info/RECORD
