Metadata-Version: 2.4
Name: cvpc
Version: 0.0.3
Summary: Computer Vision Player Core
Home-page: https://github.com/osom8979/cvpc
Author: zer0
Author-email: osom8979@gmail.com
Maintainer: zer0
Maintainer-email: osom8979@gmail.com
License: MIT License
Project-URL: GitHub: issues, https://github.com/osom8979/cvpc/issues
Project-URL: GitHub: repo, https://github.com/osom8979/cvpc
Classifier: Development Status :: 4 - Beta
Classifier: Framework :: AsyncIO
Classifier: Intended Audience :: Developers
Classifier: Operating System :: OS Independent
Classifier: Programming Language :: Python
Classifier: Programming Language :: Python :: 3.12
Classifier: Topic :: Utilities
Classifier: License :: OSI Approved :: MIT License
Requires-Python: >=3.12
License-File: LICENSE
Requires-Dist: coloredlogs==15.0.1
Requires-Dist: python-dotenv==1.0.1
Requires-Dist: uvloop==0.19.0
Dynamic: license-file
Dynamic: requires-dist
